{
  "commit": "8ae438629fae4d3c0df77c7ca24f06ba82f46570",
  "repo_url": "https://gitlab.com/gitlab-org/gitlab",
  "date": "2021-02-23T19:26:54",
  "languages": {
    "Ruby": 54869171,
    "JavaScript": 15803218,
    "Vue": 5191076,
    "Haml": 2044378,
    "PLpgSQL": 1051817,
    "SCSS": 997591,
    "Go": 654658,
    "HTML": 91334,
    "Shell": 79306,
    "CSS": 5043,
    "Makefile": 4972,
    "Dockerfile": 2839,
    "PowerShell": 561,
    "Smarty": 390,
    "Clojure": 79
  },
  "size": 80796433
}
