{
  "commit": "d118e6c477f55412f4169abb008e79532613366d",
  "repo_url": "https://gitlab.com/gitlab-org/gitlab",
  "date": "2022-05-20T11:51:20",
  "languages": {
    "Ruby": 69192343,
    "JavaScript": 20644636,
    "Vue": 7292635,
    "PLpgSQL": 2526236,
    "Haml": 2027566,
    "SCSS": 1045026,
    "Go": 743308,
    "HTML": 114309,
    "Shell": 96052,
    "Makefile": 6218,
    "CSS": 5043,
    "Dockerfile": 3950,
    "PowerShell": 575,
    "Smarty": 385,
    "Clojure": 79
  },
  "size": 103698361
}
