{
  "commit": "eda27ac9f15accb424b733b843860524a270cb32",
  "repo_url": "https://github.com/bareos/bareos",
  "date": "2017-06-21T12:36:03",
  "languages": {
    "C": 9462367,
    "C++": 1039231,
    "Shell": 559760,
    "Makefile": 203836,
    "M4": 187642,
    "RPC": 98097,
    "Python": 81502,
    "NSIS": 81495,
    "Roff": 52858,
    "HTML": 24152,
    "SuperCollider": 23329,
    "PLSQL": 17628,
    "PLpgSQL": 13409,
    "TeX": 12113,
    "Perl": 7184,
    "Vim Script": 6552,
    "QMake": 5410,
    "Batchfile": 3621,
    "sed": 711,
    "Awk": 397,
    "GDB": 329
  },
  "size": 11881623
}
